pysted/temporal.py
pysted/_draw.c
pysted/raster.c
pysted/microscopes.py
pysted/utils.py
pysted/raster.cpython-310-x86_64-linux-gnu.so
pysted/__init__.py
pysted/cUtils.cpython-310-x86_64-linux-gnu.so
pysted/exp_data_gen.py
pysted/bleach_funcs.cpython-310-x86_64-linux-gnu.so
pysted/base.py
pysted/bleach_funcs.c
pysted/_draw.cpython-310-x86_64-linux-gnu.so
pysted/cUtils.c
pysted/data/__init__.py
pysted/data/loader.py
pysted/data/examples/tubulin/2.npy
pysted/data/examples/tubulin/1.npy
pysted/data/examples/tubulin/5.npy
pysted/data/examples/tubulin/3.npy
pysted/data/examples/tubulin/4.npy
pysted/data/examples/tubulin/0.npy
pysted/data/examples/factin/2.npy
pysted/data/examples/factin/1.npy
pysted/data/examples/factin/5.npy
pysted/data/examples/factin/3.npy
pysted/data/examples/factin/4.npy
pysted/data/examples/factin/0.npy
pysted/data/examples/psd95/2.npy
pysted/data/examples/psd95/1.npy
pysted/data/examples/psd95/5.npy
pysted/data/examples/psd95/4.npy
pysted/data/examples/psd95/6.npy
pysted/data/examples/psd95/0.npy
docs/conf.py
pysted-0.0.4.dist-info/RECORD
pysted-0.0.4.dist-info/WHEEL
pysted-0.0.4.dist-info/LICENSE
pysted-0.0.4.dist-info/top_level.txt
pysted-0.0.4.dist-info/METADATA
script_templates/make_exp_video.py
script_templates/general_acq.py
examples/acquire_singledot.py
examples/acquire_stack.py
examples/acquire_noisy.py
flash_files/events_curves.npy
