Metadata-Version: 2.1
Name: pysted
Version: 0.0.4
Summary: STED image simulator in Python
Author: Anthony Bilodeau, Benoit Turcotte, Albert Michaud-Gagnon, Audrey Durand
Project-URL: Homepage, https://github.com/FLClab/pySTED
Project-URL: Issues, https://github.com/FLClab/pySTED/issues
Keywords: microscopy,sted,simulation
Classifier: Programming Language :: Python :: 3
Classifier: License :: OSI Approved :: MIT License
Classifier: Operating System :: OS Independent
Requires-Python: >=3.9
License-File: LICENSE
Requires-Dist: certifi
Requires-Dist: cycler
Requires-Dist: Cython
Requires-Dist: decorator
Requires-Dist: imageio
Requires-Dist: kiwisolver
Requires-Dist: matplotlib
Requires-Dist: networkx
Requires-Dist: numpy
Requires-Dist: pyparsing
Requires-Dist: python-dateutil
Requires-Dist: PyWavelets
Requires-Dist: scikit-image
Requires-Dist: scipy
Requires-Dist: six
Requires-Dist: tifffile
Requires-Dist: tqdm
